pylizmedia/__init__.py
pylizmedia/lizMedia.py
pylizmedia/domain/__init__.py
pylizmedia/domain/ai.py
pylizmedia/domain/audio.py
pylizmedia/domain/frame.py
pylizmedia/domain/video.py
pylizmedia/log/__init__.py
pylizmedia/log/pylizLogger.py
pylizmedia/util/__init__.py
pylizmedia/util/frame.py
pylizmedia/util/image.py
pylizmedia/util/video.py
test/__init__.py
test/test_video.py
pylizmedia-0.0.21.dist-info/METADATA
pylizmedia-0.0.21.dist-info/WHEEL
pylizmedia-0.0.21.dist-info/top_level.txt
pylizmedia-0.0.21.dist-info/RECORD
