Metadata-Version: 2.4
Name: pylizmedia
Version: 0.0.21
Summary: Add your description here
Author: Gabliz
Author-email: 
Requires-Python: >=3.12
Requires-Dist: ffmpeg-python>=0.2.0
Requires-Dist: numpy>=2.2.5
Requires-Dist: opencv-python>=4.11.0.86
Requires-Dist: packaging>=25.0
Requires-Dist: pillow>=11.2.1
Requires-Dist: pydantic>=2.11.3
Requires-Dist: pylizlib>=0.1.45
Requires-Dist: sd-parsers>=0.6
Dynamic: author
